SG_Boilerplate-1.7.0.data/scripts/boilerplate-cli
SG_boilerplate/__init__.py
SG_boilerplate/importable.py
SG_Boilerplate-1.7.0.dist-info/METADATA
SG_Boilerplate-1.7.0.dist-info/WHEEL
SG_Boilerplate-1.7.0.dist-info/top_level.txt
SG_Boilerplate-1.7.0.dist-info/RECORD
