Metadata-Version: 2.1
Name: SG-Boilerplate
Version: 1.7.0
Summary: This is a description.
Home-page: UNKNOWN
License: UNKNOWN
Platform: UNKNOWN
Requires-Python: >=3.6.3
Requires-Dist: colored (==1.3.93)
